{
    "angle": 90, 
    "blades": [
        {
            "backscatter": 1.26, 
            "inclination": 0, 
            "substrate": 0, 
            "transmission": 1.3
        }, 
        {
            "backscatter": 1.32, 
            "inclination": 0, 
            "substrate": 0, 
            "transmission": 1.3
        }, 
        {
            "backscatter": 1.48, 
            "inclination": 0, 
            "substrate": 0, 
            "transmission": 1.3
        }, 
        {
            "backscatter": 1.74, 
            "inclination": 0, 
            "substrate": 0, 
            "transmission": 1.3
        }, 
        {
            "backscatter": 2.06, 
            "inclination": 0, 
            "substrate": 0, 
            "transmission": 1.3
        }, 
        {
            "backscatter": 2.43, 
            "inclination": 0, 
            "substrate": 0, 
            "transmission": 1.3
        }, 
        {
            "backscatter": 2.88, 
            "inclination": 0, 
            "substrate": 0, 
            "transmission": 1.3
        }
    ], 
    "converterConfiguration": null, 
    "name": "Detector", 
    "single": false, 
    "threshold": 100, 
    "wavelength": [
        {
            "%": 100, 
            "angstrom": 1.8
        }
    ]
}